<?xml version="1.0" encoding="UTF-8"?><record_update sys_domain="global" table="sysevent_email_action">
    <sysevent_email_action action="INSERT_OR_UPDATE">
        <action_insert>false</action_insert>
        <action_update>true</action_update>
        <active>true</active>
        <advanced_condition/>
        <affected_field_on_event/>
        <category display_value="Uncategorized" name="Uncategorized">c97d83137f4432005f58108c3ffa917a</category>
        <collection>x_137031_qc_corrective_action_task</collection>
        <condition table="x_137031_qc_corrective_action_task">stateCHANGESTO14^EQ<item display_value="Pending Response" endquery="false" field="state" goto="false" newquery="false" operator="CHANGESTO" or="false" value="14"/>
            <item endquery="true" field="" goto="false" newquery="false" operator="=" or="false" value=""/>
        </condition>
        <content_type>text/html</content_type>
        <default_interval/>
        <description/>
        <digest_from/>
        <digest_html/>
        <digest_reply_to/>
        <digest_separator_html><![CDATA[<p>&nbsp;</p>
<hr />
<p>&nbsp;</p>]]></digest_separator_html>
        <digest_separator_text><![CDATA[\n--------------------------------------------------------------------------------\n]]></digest_separator_text>
        <digest_subject/>
        <digest_template/>
        <digest_text/>
        <digestable>false</digestable>
        <event_name>alm_transfer_order_line_subtask.escalati</event_name>
        <event_parm_1>false</event_parm_1>
        <event_parm_2>false</event_parm_2>
        <exclude_delegates>false</exclude_delegates>
        <force_delivery>false</force_delivery>
        <from/>
        <generation_type>engine</generation_type>
        <importance/>
        <include_attachments>false</include_attachments>
        <item>event.parm1</item>
        <item_table/>
        <mandatory>false</mandatory>
        <message/>
        <message_html><![CDATA[<p>Attention ${supplier_contact},</p>
<p>A Supplier Corrective Action Task, reference number ${number} has been created as a result of an internal request from Tredegar Corporation Quality Control with the following information:</p>
<p><strong>${parent.number}</strong><br /><strong>Supplier Name:</strong> ${supplier_name} <br /><strong>Plant:</strong> ${plant}<br /><strong>Issue Type:</strong> ${issue_type}</p>
<p><strong>Short description:</strong> ${short_description}<br /><strong>Description:</strong> ${description}</p>
<p>Your Tredegar contact for this matter is:</p>
<p><strong>Name:</strong> ${assigned_to.first_name} ${assigned_to.last_name}<br /><strong>Email:</strong> ${assigned_to.email}</p>
<p><br /><strong>Please reply to this email with the following required fields below. </strong></p>
<p><strong>Please respond in-line after the ":" and leave your Reply empty unless you have additional comments.</strong></p>
<p>&nbsp;</p>
<p>Thank you,</p>
<p>&nbsp;</p>
<p><strong>## PLEASE RESPOND TO THESE FIELDS BELOW ##</strong></p>
<p>Investigation Results:</p>
<p>Root Cause:</p>
<p>Return Auth Number:</p>]]></message_html>
        <message_list/>
        <message_text/>
        <name>Notify Supplier</name>
        <omit_watermark>false</omit_watermark>
        <order>100</order>
        <push_message_only>false</push_message_only>
        <recipient_fields>supplier_contact</recipient_fields>
        <recipient_groups/>
        <recipient_users/>
        <reply_to/>
        <send_self>true</send_self>
        <sms_alternate/>
        <style/>
        <subject>Corrective Action Task ${number} has been assigned to you</subject>
        <subscribable>false</subscribable>
        <sys_class_name>sysevent_email_action</sys_class_name>
        <sys_created_by>luke.marsh</sys_created_by>
        <sys_created_on>2019-09-27 13:36:52</sys_created_on>
        <sys_domain>global</sys_domain>
        <sys_domain_path>/</sys_domain_path>
        <sys_id>a1b0081b1b04c0107f81da49cc4bcbed</sys_id>
        <sys_mod_count>19</sys_mod_count>
        <sys_name>Notify Supplier</sys_name>
        <sys_overrides/>
        <sys_package display_value="SCAR" source="x_137031_qc">d78b7e501b8c00107f81da49cc4bcbd6</sys_package>
        <sys_policy/>
        <sys_scope display_value="SCAR">d78b7e501b8c00107f81da49cc4bcbd6</sys_scope>
        <sys_update_name>sysevent_email_action_a1b0081b1b04c0107f81da49cc4bcbed</sys_update_name>
        <sys_updated_by>todd.fudala</sys_updated_by>
        <sys_updated_on>2019-10-09 19:13:32</sys_updated_on>
        <sys_version>2</sys_version>
        <template display_value="Unsubscribe and Preferences">7ed0481f3b0b2200c869c2c703efc487</template>
        <type>email</type>
        <weight>0</weight>
    </sysevent_email_action>
</record_update>
